tANS_py/Coder.py
tANS_py/Decoder.py
tANS_py/Encoder.py
tANS_py/SpreadFunction.py
tANS_py/Utils.py
tANS_py/__init__.py
tANS_py/tANS.py
tans_py-0.1.7.dist-info/METADATA
tans_py-0.1.7.dist-info/WHEEL
tans_py-0.1.7.dist-info/licenses/LICENSE
tans_py-0.1.7.dist-info/RECORD
