Metadata-Version: 2.3
Name: tANS_py
Version: 0.1.7
Summary: A Python implementation of the tANS algorithm
Project-URL: Homepage, https://pypi.org/project/tANS-py/
Project-URL: Repository, https://github.com/adamrt27/tANS_py
Author-email: Adam Taback <adamrtaback@gmail.com>
License-File: LICENSE
Classifier: License :: OSI Approved :: MIT License
Classifier: Operating System :: OS Independent
Classifier: Programming Language :: Python :: 3
Requires-Python: >=3.6
Requires-Dist: numpy
Requires-Dist: pandas
